eigenlearn/__init__.py
eigenlearn/eigenlearn.py
eigenlearn/main.py
eigenlearn/utils.py
eigenlearn-0.0.5.dist-info/LICENSE
eigenlearn-0.0.5.dist-info/METADATA
eigenlearn-0.0.5.dist-info/WHEEL
eigenlearn-0.0.5.dist-info/top_level.txt
eigenlearn-0.0.5.dist-info/RECORD
