Metadata-Version: 2.1
Name: eigenlearn
Version: 0.0.5
Summary: A package for matrix denoising and completion by learning eigen vectors
Home-page: https://github.com/pypa/sampleproject
Author: amir shamaei
Author-email: amirshamaei@isibrno.cz
Project-URL: Bug Tracker, https://github.com/pypa/sampleproject/issues
Classifier: Programming Language :: Python :: 3
Classifier: License :: OSI Approved :: MIT License
Classifier: Operating System :: OS Independent
Requires-Python: >=3.6
License-File: LICENSE
